tglc/__init__.py
tglc/effective_psf.py
tglc/ffi.py
tglc/ffi_cut.py
tglc/lc_plot.py
tglc/mast.py
tglc/quick_lc.py
tglc/run.py
tglc/source_output.py
tglc/target_lightcurve.py
tglc/background_mask/__init__.py
tglc/background_mask/median_mask.fits
tglc-0.6.5.dist-info/LICENSE
tglc-0.6.5.dist-info/METADATA
tglc-0.6.5.dist-info/WHEEL
tglc-0.6.5.dist-info/top_level.txt
tglc-0.6.5.dist-info/RECORD
