Metadata-Version: 2.1
Name: tglc
Version: 0.6.5
Summary: TESS-Gaia Light Curve
Home-page: https://github.com/TeHanHunter/TESS_Gaia_Light_Curve
Author: Te Han
Author-email: tehanhunter@gmail.com
Classifier: Programming Language :: Python :: 3
Classifier: License :: OSI Approved :: MIT License
Classifier: Operating System :: OS Independent
Requires-Python: >=3.8
License-File: LICENSE
Requires-Dist: astropy >=5.1
Requires-Dist: astroquery
Requires-Dist: matplotlib
Requires-Dist: numpy
Requires-Dist: oauthlib
Requires-Dist: requests
Requires-Dist: scipy
Requires-Dist: threadpoolctl
Requires-Dist: tqdm
Requires-Dist: wheel
Requires-Dist: wotan
